{
	"Version": 3,
	"Meta": {
		"Duration": 2.2,
		"Fps": 30.0,
		"Loop": true,
		"AreBeziersRestricted": false,
		"CurveCount": 7,
		"TotalSegmentCount": 20,
		"TotalPointCount": 59,
		"UserDataCount": 0,
		"TotalUserDataSize": 0
	},
	"Curves": [
		{
			"Target": "Parameter",
			"Id": "ParamAngleX",
			"Segments": [
				0,
				0,
				1,
				0.111,
				0,
				0.222,
				-10,
				0.333,
				-10,
				1,
				0.778,
				-10,
				1.222,
				15,
				1.667,
				15,
				1,
				1.844,
				15,
				2.022,
				0,
				2.2,
				0
			]
		},
		{
			"Target": "Parameter",
			"Id": "ParamAngleZ",
			"Segments": [
				0,
				0,
				1,
				0.111,
				0,
				0.222,
				-8,
				0.333,
				-8,
				1,
				0.578,
				-8,
				0.822,
				-7.101,
				1.067,
				0,
				1,
				1.267,
				5.81,
				1.467,
				16,
				1.667,
				16,
				1,
				1.844,
				16,
				2.022,
				0,
				2.2,
				0
			]
		},
		{
			"Target": "Parameter",
			"Id": "ParamEyeLOpen",
			"Segments": [
				0,
				1,
				1,
				0.111,
				1,
				0.222,
				1,
				0.333,
				1,
				1,
				0.578,
				1,
				0.822,
				0.7,
				1.067,
				0.7,
				1,
				1.267,
				0.7,
				1.467,
				1,
				1.667,
				1,
				1,
				1.844,
				1,
				2.022,
				1,
				2.2,
				1
			]
		},
		{
			"Target": "Parameter",
			"Id": "ParamEyeROpen",
			"Segments": [
				0,
				1,
				1,
				0.111,
				1,
				0.222,
				1,
				0.333,
				1,
				1,
				0.578,
				1,
				0.822,
				0.7,
				1.067,
				0.7,
				1,
				1.267,
				0.7,
				1.467,
				1,
				1.667,
				1,
				1,
				1.844,
				1,
				2.022,
				1,
				2.2,
				1
			]
		},
		{
			"Target": "Parameter",
			"Id": "ParamEyeLSmile",
			"Segments": [
				0,
				0,
				0,
				2.2,
				0
			]
		},
		{
			"Target": "Parameter",
			"Id": "Param",
			"Segments": [
				0,
				0,
				0,
				1.067,
				0,
				1,
				1.267,
				0,
				1.467,
				0,
				1.667,
				0,
				0,
				2.2,
				0
			]
		},
		{
			"Target": "Parameter",
			"Id": "Param2",
			"Segments": [
				0,
				30,
				0,
				2.2,
				30
			]
		}
	]
}